{"9":{"transport":1,"price":227,"duration":915},"10":{"transport":1,"price":209,"duration":2565},"11":{"transport":1,"price":391,"duration":1215},"13":{"transport":1,"price":355,"duration":905},"14":{"transport":1,"price":417,"duration":1230},"15":{"transport":1,"price":327,"duration":1080},"16":{"transport":1,"price":543,"duration":1310},"17":{"transport":1,"price":164,"duration":840},"18":{"transport":1,"price":309,"duration":1030},"20":{"transport":1,"price":291,"duration":925},"21":{"transport":1,"price":446,"duration":1515},"22":{"transport":1,"price":267,"duration":710},"23":{"transport":1,"price":291,"duration":1120},"24":{"transport":1,"price":401,"duration":1095},"25":{"transport":1,"price":200,"duration":880},"26":{"transport":1,"price":118,"duration":620},"27":{"transport":1,"price":409,"duration":1415},"28":{"transport":1,"price":236,"duration":800},"29":{"transport":1,"price":255,"duration":1000},"30":{"transport":1,"price":182,"duration":840},"31":{"transport":1,"price":41,"duration":755},"32":{"transport":1,"price":236,"duration":845},"33":{"transport":1,"price":118,"duration":685},"34":{"transport":1,"price":73,"duration":855},"35":{"transport":1,"price":68,"duration":890},"36":{"transport":1,"price":409,"duration":1334},"37":{"transport":1,"price":291,"duration":945},"38":{"transport":1,"price":273,"duration":825},"39":{"transport":1,"price":291,"duration":1088},"40":{"transport":1,"price":291,"duration":1000},"42":{"transport":1,"price":346,"duration":726},"43":{"transport":1,"price":309,"duration":1045},"44":{"transport":1,"price":170,"duration":865},"45":{"transport":1,"price":85,"duration":855},"48":{"transport":1,"price":482,"duration":1240},"55":{"transport":1,"price":311,"duration":1060},"56":{"transport":1,"price":233,"duration":975},"57":{"transport":1,"price":300,"duration":1065},"58":{"transport":1,"price":200,"duration":530},"59":{"transport":1,"price":450,"duration":845},"61":{"transport":1,"price":582,"duration":1130},"62":{"transport":1,"price":369,"duration":805},"63":{"transport":1,"price":402,"duration":750},"64":{"transport":1,"price":396,"duration":1180},"66":{"transport":1,"price":267,"duration":960},"67":{"transport":1,"price":480,"duration":1255},"68":{"transport":1,"price":500,"duration":1280},"69":{"transport":1,"price":235,"duration":705},"70":{"transport":1,"price":627,"duration":2075},"71":{"transport":1,"price":384,"duration":1385},"72":{"transport":1,"price":607,"duration":1735},"73":{"transport":1,"price":637,"duration":1765},"74":{"transport":1,"price":108,"duration":455},"75":{"transport":1,"price":446,"duration":1370},"76":{"transport":1,"price":426,"duration":1230},"77":{"transport":1,"price":373,"duration":1345},"78":{"transport":1,"price":136,"duration":595},"80":{"transport":1,"price":517,"duration":1270},"81":{"transport":1,"price":418,"duration":1270},"82":{"transport":1,"price":490,"duration":1115},"83":{"transport":1,"price":380,"duration":1025},"84":{"transport":1,"price":206,"duration":865},"85":{"transport":1,"price":397,"duration":1045},"86":{"transport":1,"price":145,"duration":775},"87":{"transport":1,"price":437,"duration":1170},"89":{"transport":1,"price":619,"duration":1220},"90":{"transport":1,"price":427,"duration":1150},"91":{"transport":1,"price":267,"duration":940},"93":{"transport":1,"price":256,"duration":735},"94":{"transport":1,"price":475,"duration":1265},"95":{"transport":1,"price":248,"duration":715},"96":{"transport":1,"price":426,"duration":1035},"98":{"transport":1,"price":373,"duration":985},"99":{"transport":1,"price":344,"duration":1195},"101":{"transport":1,"price":30,"duration":290},"103":{"transport":1,"price":30,"duration":655},"104":{"transport":1,"price":26,"duration":460},"105":{"transport":1,"price":27,"duration":395},"106":{"transport":1,"price":80,"duration":445},"107":{"transport":1,"price":56,"duration":395},"111":{"transport":1,"price":25,"duration":200},"113":{"transport":1,"price":99,"duration":610},"114":{"transport":1,"price":61,"duration":465},"116":{"transport":1,"price":20,"duration":365},"119":{"transport":1,"price":34,"duration":325},"121":{"transport":2,"price":10,"duration":20},"123":{"transport":1,"price":26,"duration":405},"124":{"transport":1,"price":20,"duration":345},"126":{"transport":1,"price":70,"duration":315},"127":{"transport":1,"price":27,"duration":390},"128":{"transport":1,"price":23,"duration":335},"129":{"transport":1,"price":36,"duration":390},"130":{"transport":1,"price":30,"duration":370},"131":{"transport":1,"price":52,"duration":395},"132":{"transport":1,"price":77,"duration":670},"134":{"transport":1,"price":27,"duration":435},"135":{"transport":1,"price":55,"duration":400},"137":{"transport":1,"price":30,"duration":395},"140":{"transport":1,"price":30,"duration":325},"146":{"transport":1,"price":80,"duration":475},"147":{"transport":1,"price":23,"duration":345},"150":{"transport":1,"price":19,"duration":395},"151":{"transport":1,"price":60,"duration":455},"152":{"transport":1,"price":50,"duration":575},"155":{"transport":1,"price":50,"duration":1075},"160":{"transport":1,"price":75,"duration":605},"161":{"transport":1,"price":50,"duration":365},"162":{"transport":1,"price":236,"duration":185},"163":{"transport":1,"price":40,"duration":545},"164":{"transport":1,"price":85,"duration":380},"166":{"transport":1,"price":245,"duration":230},"171":{"transport":1,"price":38,"duration":855},"174":{"transport":1,"price":65,"duration":330},"176":{"transport":1,"price":100,"duration":535},"177":{"transport":1,"price":55,"duration":375},"178":{"transport":1,"price":52,"duration":780},"179":{"transport":1,"price":35,"duration":385},"180":{"transport":1,"price":65,"duration":490},"181":{"transport":1,"price":85,"duration":850},"184":{"transport":1,"price":28,"duration":205},"186":{"transport":1,"price":55,"duration":525},"187":{"transport":1,"price":41,"duration":575},"191":{"transport":1,"price":23,"duration":400},"192":{"transport":1,"price":30,"duration":335},"193":{"transport":1,"price":20,"duration":415},"196":{"transport":1,"price":30,"duration":335},"197":{"transport":1,"price":70,"duration":330},"200":{"transport":1,"price":110,"duration":505},"201":{"transport":1,"price":60,"duration":430},"202":{"transport":1,"price":65,"duration":425},"205":{"transport":1,"price":27,"duration":385},"206":{"transport":1,"price":113,"duration":530},"207":{"transport":1,"price":100,"duration":570},"213":{"transport":1,"price":98,"duration":580},"214":{"transport":1,"price":25,"duration":365},"218":{"transport":1,"price":85,"duration":1095},"225":{"transport":2,"price":18,"duration":155},"227":{"transport":1,"price":95,"duration":525},"228":{"transport":1,"price":40,"duration":585},"230":{"transport":1,"price":35,"duration":640},"231":{"transport":1,"price":45,"duration":600},"233":{"transport":1,"price":20,"duration":340},"235":{"transport":1,"price":28,"duration":450},"236":{"transport":1,"price":35,"duration":450},"242":{"transport":1,"price":82,"duration":720},"243":{"transport":1,"price":79,"duration":170},"247":{"transport":1,"price":30,"duration":325},"248":{"transport":1,"price":23,"duration":395},"249":{"transport":1,"price":30,"duration":405},"250":{"transport":1,"price":60,"duration":420},"251":{"transport":1,"price":55,"duration":440},"252":{"transport":1,"price":32,"duration":350},"253":{"transport":1,"price":40,"duration":410},"257":{"transport":1,"price":109,"duration":510},"259":{"transport":1,"price":23,"duration":375},"261":{"transport":1,"price":45,"duration":380},"264":{"transport":1,"price":79,"duration":335},"266":{"transport":1,"price":27,"duration":375},"267":{"transport":1,"price":29,"duration":465},"270":{"transport":1,"price":35,"duration":320},"274":{"transport":1,"price":32,"duration":325},"275":{"transport":1,"price":50,"duration":445},"277":{"transport":1,"price":48,"duration":380},"284":{"transport":1,"price":29,"duration":370},"285":{"transport":1,"price":32,"duration":495},"287":{"transport":1,"price":35,"duration":365},"288":{"transport":1,"price":95,"duration":510},"289":{"transport":1,"price":41,"duration":540},"290":{"transport":1,"price":100,"duration":660},"291":{"transport":1,"price":45,"duration":375},"293":{"transport":1,"price":20,"duration":305},"295":{"transport":1,"price":30,"duration":905},"297":{"transport":1,"price":23,"duration":330},"299":{"transport":1,"price":95,"duration":470},"300":{"transport":1,"price":191,"duration":460},"302":{"transport":1,"price":79,"duration":365},"303":{"transport":1,"price":41,"duration":385},"305":{"transport":1,"price":22,"duration":425},"308":{"transport":1,"price":80,"duration":215},"309":{"transport":1,"price":27,"duration":915},"311":{"transport":1,"price":85,"duration":40},"314":{"transport":1,"price":36,"duration":530},"316":{"transport":1,"price":75,"duration":370},"317":{"transport":1,"price":80,"duration":485},"318":{"transport":1,"price":30,"duration":315},"320":{"transport":1,"price":27,"duration":435},"321":{"transport":1,"price":68,"duration":390},"325":{"transport":1,"price":52,"duration":370},"326":{"transport":1,"price":350,"duration":330},"327":{"transport":1,"price":33,"duration":385},"329":{"transport":1,"price":21,"duration":400},"330":{"transport":1,"price":55,"duration":510},"331":{"transport":1,"price":40,"duration":550},"332":{"transport":1,"price":50,"duration":540},"335":{"transport":1,"price":30,"duration":355},"336":{"transport":1,"price":40,"duration":560},"337":{"transport":1,"price":35,"duration":1000},"338":{"transport":1,"price":36,"duration":645},"339":{"transport":1,"price":118,"duration":695},"341":{"transport":1,"price":28,"duration":535},"342":{"transport":1,"price":29,"duration":330},"345":{"transport":1,"price":65,"duration":405},"347":{"transport":1,"price":104,"duration":700},"348":{"transport":1,"price":21,"duration":365},"351":{"transport":1,"price":45,"duration":370},"353":{"transport":1,"price":27,"duration":350},"354":{"transport":1,"price":45,"duration":415},"356":{"transport":1,"price":68,"duration":594},"357":{"transport":1,"price":25,"duration":560},"359":{"transport":1,"price":113,"duration":1025},"364":{"transport":1,"price":23,"duration":585},"365":{"transport":1,"price":18,"duration":390},"368":{"transport":1,"price":24,"duration":380},"370":{"transport":1,"price":30,"duration":285},"371":{"transport":1,"price":32,"duration":675},"547":{"transport":1,"price":327,"duration":1245},"548":{"transport":1,"price":364,"duration":1180},"552":{"transport":1,"price":311,"duration":715},"554":{"transport":1,"price":256,"duration":935},"626":{"transport":1,"price":344,"duration":1255},"663":{"transport":1,"price":373,"duration":915}}